falconai/__init__.py
falconai/main.py
falconai-0.0.3.dist-info/METADATA
falconai-0.0.3.dist-info/WHEEL
falconai-0.0.3.dist-info/top_level.txt
falconai-0.0.3.dist-info/RECORD
