Metadata-Version: 2.4
Name: falconai
Version: 0.0.3
Summary: The ultimate library for building generative AI apps with one line of code, offering support for 10,000+ models, browser automation, and advanced agent workflows via MCP.
Author: FalconAI
Author-email: falconai.dev@gmail.com
Requires-Dist: litellm
Requires-Dist: langchain_community
Requires-Dist: beautifulsoup4
Requires-Dist: docx2txt
Requires-Dist: bs4
Requires-Dist: pyttsx3
Requires-Dist: browser-use
Requires-Dist: playwright
Requires-Dist: duckduckgo-search
Requires-Dist: langchain-openai
Requires-Dist: langchain-anthropic
Requires-Dist: langchain-google-genai
Requires-Dist: httpx
Requires-Dist: duckduckgo_search
Requires-Dist: duckai
Requires-Dist: crawl4ai
Requires-Dist: mcp-use
Requires-Dist: pypdf
Requires-Dist: youtube-transcript-api
Requires-Dist: langchain-groq
Requires-Dist: langchain-xai
Requires-Dist: langchain-deepseek
Requires-Dist: langchain-community
Dynamic: author
Dynamic: author-email
Dynamic: description
Dynamic: description-content-type
Dynamic: requires-dist
Dynamic: summary
